tests/__init__.py
tests/samples.py
tests/test_paths.py
wildpath/__init__.py
wildpath/keyparser.py
wildpath/paths.py
wildpath/tools.py
wildpath-0.2.7.dist-info/DESCRIPTION.rst
wildpath-0.2.7.dist-info/METADATA
wildpath-0.2.7.dist-info/RECORD
wildpath-0.2.7.dist-info/WHEEL
wildpath-0.2.7.dist-info/metadata.json
wildpath-0.2.7.dist-info/top_level.txt
