Metadata-Version: 2.0
Name: wildpath
Version: 0.2.7
Summary: easy data structure access utility
Home-page: UNKNOWN
Author: Lars van Gemerden
Author-email: gemerden@gmail.com
License: MIT License
Keywords: access data structure getter setter deleter iterator utility tool path wildcard slice
Platform: UNKNOWN
Classifier: Development Status :: 4 - Beta
Classifier: Intended Audience :: Developers
Classifier: Topic :: Software Development
Classifier: License :: OSI Approved :: MIT License
Classifier: Programming Language :: Python :: 2
Classifier: Programming Language :: Python :: 2.7
Classifier: Programming Language :: Python :: 3
Classifier: Programming Language :: Python :: 3.3
Classifier: Programming Language :: Python :: 3.4
Classifier: Programming Language :: Python :: 3.5
Classifier: Programming Language :: Python :: 3.6
Requires-Dist: boolean.py
